Workbook

Sheet 0_SKU
A1: sku_code | B1: bundles_per_master_carton | C1: cost_per_bundle | D1: seed_master_carton_cost | E1: pool_unit_price | F1: sku_description
A2: A1 | B2: 10 | C2: =D2/B2 | D2: 135 | E2: 15 | F2: 22oz PP Cups + Flat Lids (10 bundles x 100 pcs)
A3: A2 | B3: 10 | C3: =D3/B3 | D3: 120 | E3: 13.5 | F3: 16oz PP Cups + Dome Lids (10 bundles x 100 pcs)
A4: B1 | B4: 10 | C4: =D4/B4 | D4: 110 | E4: 12.5 | F4: 750ml Rectangular Food Container + Lids (10 bundles x 50 pcs)
A5: C1 | B5: 12 | C5: =D5/B5 | D5: 144 | E5: 13.5 | F5: Kraft Brown Lunch Box (12 bundles x 50 pcs)
A6: D1 | B6: 8 | C6: =D6/B6 | D6: 160 | E6: 21 | F6: Evaporated / Condensed Milk Carton (8 bundles x 6 tins)
A7: E1 | B7: 10 | C7: =D7/B7 | D7: 90 | E7: 10.5 | F7: Takeaway Singlet Oxo-Bag + Straw Bundle (10 bundles)

Sheet 1_Stalls
A1: stall_id | B1: stall_name | C1: cluster | D1: stall_number | E1: whatsapp_phone | F1: written_language | G1: trust_tier | H1: basket_tier | I1: onboarding_date | J1: is_active
A2: S01 | B2: Ah Seng Teh C Peng Special | C2: Premier 101 | D2: P101-01 | E2: +60128812341 | F2: zh-CN | G2: ANCHOR_PRIORITY | H2: T1 | I2: 2026-10-10 | J2: TRUE
A3: S02 | B3: Kak Nor Nasi Lemak & Laksa | C3: Premier 101 | D3: P101-08 | E3: +60198765432 | F3: ms-MY | G3: COD_APPROVED | H3: T2 | I3: 2026-10-10 | J3: TRUE
A4: S03 | B4: Uncle Wong Kolo Mee | C4: Premier 101 | D4: P101-12 | E4: +60168551122 | F4: zh-CN | G4: COD_APPROVED | H4: T2 | I4: 2026-10-11 | J4: TRUE
A5: S04 | B5: Borneo Shake & Juice | C5: Premier 101 | D5: P101-15 | E5: +60138009988 | F5: en | G5: COD_APPROVED | H5: T1 | I5: 2026-10-11 | J5: TRUE
A6: S05 | B6: Abang Zul Burger & Oblong | C6: Premier 101 | D6: P101-22 | E6: +60178443321 | F6: ms-MY | G6: PROVISIONAL | H6: T3 | I6: 2026-10-12 | J6: TRUE
A7: S06 | B7: Gala Haus Bubble Tea | C7: Gala City | D7: GC-03 | E7: +601123456789 | F7: zh-CN | G7: ANCHOR_PRIORITY | H7: T1 | I7: 2026-10-12 | J7: TRUE
A8: S07 | B8: Golden Wok Char Kuey Teow | C8: Gala City | D8: GC-09 | E8: +60148227766 | F8: zh-CN | G8: COD_APPROVED | H8: T2 | I8: 2026-10-13 | J8: TRUE
A9: S08 | B9: Dapur Maksu Ayam Gepuk | C9: Gala City | D9: GC-14 | E9: +60198112233 | F9: ms-MY | G9: COD_APPROVED | H9: T2 | I9: 2026-10-13 | J9: TRUE
A10: S09 | B10: Kopi & Toast Corner | C10: Gala City | D10: GC-19 | E10: +60168990011 | F10: en | G10: COD_APPROVED | H10: T2 | I10: 2026-10-14 | J10: TRUE
A11: S10 | B11: Lok Lok Bros | C11: Gala City | D11: GC-25 | F11: zh-CN | G11: PROVISIONAL | H11: T3 | I11: 2026-10-22 | J11: TRUE

Sheet 2_Orders
A1: batch_id | B1: delivery_date | C1: stall_id | D1: sku_code | E1: order_type | F1: ordered_bundles | G1: delivered_bundles | H1: unit_price | I1: payment_status | J1: fulfilment_status | K1: payment_reference | L1: source | M1: notes | N1: revenue | O1: gp | P1: cost
A2: B01 | B2: 2026-10-15 | C2: S01 | D2: A1 | E2: PREORDER | F2: 10 | G2: 10 | H2: 15 | I2: PAID_DUITNOW | J2: DELIVERED | K2: 4821 | L2: TEXT | M2: Anchor drink stall | N2: =H2*G2 | O2: =(H2-VLOOKUP(D2,'0_SKU'!$A$2:$C$7,3,FALSE))*G2 | P2: =VLOOKUP(D2,'0_SKU'!$A$2:$C$7,3,FALSE)*G2
A3: B01 | B3: 2026-10-15 | C3: S01 | D3: D1 | E3: PREORDER | F3: 6 | G3: 6 | H3: 21 | I3: PAID_DUITNOW | J3: DELIVERED | K3: 4821 | L3: TEXT | M3: Bought milk w/ cups | N3: =H3*G3 | O3: =(H3-VLOOKUP(D3,'0_SKU'!$A$2:$C$7,3,FALSE))*G3 | P3: =VLOOKUP(D3,'0_SKU'!$A$2:$C$7,3,FALSE)*G3
A4: B01 | B4: 2026-10-15 | C4: S02 | D4: B1 | E4: PREORDER | F4: 8 | G4: 8 | H4: 12.5 | I4: PAID_CASH | J4: DELIVERED | L4: VOICE_FOUNDER | M4: Called founder directly | N4: =H4*G4 | O4: =(H4-VLOOKUP(D4,'0_SKU'!$A$2:$C$7,3,FALSE))*G4 | P4: =VLOOKUP(D4,'0_SKU'!$A$2:$C$7,3,FALSE)*G4
A5: B01 | B5: 2026-10-15 | C5: S02 | D5: E1 | E5: PREORDER | F5: 5 | G5: 5 | H5: 10.5 | I5: PAID_CASH | J5: DELIVERED | L5: VOICE_FOUNDER | M5: Added takeaway bags | N5: =H5*G5 | O5: =(H5-VLOOKUP(D5,'0_SKU'!$A$2:$C$7,3,FALSE))*G5 | P5: =VLOOKUP(D5,'0_SKU'!$A$2:$C$7,3,FALSE)*G5
A6: B01 | B6: 2026-10-15 | C6: S03 | D6: C1 | E6: PREORDER | F6: 10 | G6: 10 | H6: 13.5 | I6: PAID_CASH | J6: DELIVERED | L6: TEXT | M6: Mentioned C1 price only RM0.50 cheaper | N6: =H6*G6 | O6: =(H6-VLOOKUP(D6,'0_SKU'!$A$2:$C$7,3,FALSE))*G6 | P6: =VLOOKUP(D6,'0_SKU'!$A$2:$C$7,3,FALSE)*G6
A7: B01 | B7: 2026-10-15 | C7: S04 | D7: A1 | E7: PREORDER | F7: 8 | G7: 8 | H7: 15 | I7: PAID_DUITNOW | J7: DELIVERED | K7: 5510 | L7: TEXT | M7: Juice stall cup restock | N7: =H7*G7 | O7: =(H7-VLOOKUP(D7,'0_SKU'!$A$2:$C$7,3,FALSE))*G7 | P7: =VLOOKUP(D7,'0_SKU'!$A$2:$C$7,3,FALSE)*G7
A8: B01 | B8: 2026-10-15 | C8: S04 | D8: A2 | E8: PREORDER | F8: 8 | G8: 8 | H8: 13.5 | I8: PAID_DUITNOW | J8: DELIVERED | K8: 5510 | L8: TEXT | M8: 16oz smoothie dome cups | N8: =H8*G8 | O8: =(H8-VLOOKUP(D8,'0_SKU'!$A$2:$C$7,3,FALSE))*G8 | P8: =VLOOKUP(D8,'0_SKU'!$A$2:$C$7,3,FALSE)*G8
A9: B01 | B9: 2026-10-15 | C9: S05 | D9: B1 | E9: PREORDER | F9: 8 | G9: 4 | H9: 12.5 | I9: PAID_CASH | J9: PARTIAL | L9: TEXT | M9: Only had cash for 4 bundles at stall | N9: =H9*G9 | O9: =(H9-VLOOKUP(D9,'0_SKU'!$A$2:$C$7,3,FALSE))*G9 | P9: =VLOOKUP(D9,'0_SKU'!$A$2:$C$7,3,FALSE)*G9
A10: B01 | B10: 2026-10-15 | C10: S06 | D10: A1 | E10: PREORDER | F10: 10 | G10: 10 | H10: 15 | I10: PAID_DUITNOW | J10: DELIVERED | K10: 9012 | L10: TEXT | M10: Fast QR payment | N10: =H10*G10 | O10: =(H10-VLOOKUP(D10,'0_SKU'!$A$2:$C$7,3,FALSE))*G10 | P10: =VLOOKUP(D10,'0_SKU'!$A$2:$C$7,3,FALSE)*G10
A11: B01 | B11: 2026-10-15 | C11: S06 | D11: A2 | E11: PREORDER | F11: 10 | G11: 10 | H11: 13.5 | I11: PAID_DUITNOW | J11: DELIVERED | K11: 9012 | L11: TEXT | M11: Gala City anchor drink stall | N11: =H11*G11 | O11: =(H11-VLOOKUP(D11,'0_SKU'!$A$2:$C$7,3,FALSE))*G11 | P11: =VLOOKUP(D11,'0_SKU'!$A$2:$C$7,3,FALSE)*G11
A12: B01 | B12: 2026-10-15 | C12: S07 | D12: C1 | E12: PREORDER | F12: 10 | G12: 10 | H12: 13.5 | I12: PAID_CASH | J12: DELIVERED | L12: TEXT | M12: Char Kuey Teow lunch boxes | N12: =H12*G12 | O12: =(H12-VLOOKUP(D12,'0_SKU'!$A$2:$C$7,3,FALSE))*G12 | P12: =VLOOKUP(D12,'0_SKU'!$A$2:$C$7,3,FALSE)*G12
A13: B01 | B13: 2026-10-15 | C13: S07 | D13: E1 | E13: PREORDER | F13: 5 | G13: 5 | H13: 10.5 | I13: PAID_CASH | J13: DELIVERED | L13: TEXT | M13: Singlet bags & straws | N13: =H13*G13 | O13: =(H13-VLOOKUP(D13,'0_SKU'!$A$2:$C$7,3,FALSE))*G13 | P13: =VLOOKUP(D13,'0_SKU'!$A$2:$C$7,3,FALSE)*G13
A14: B01 | B14: 2026-10-15 | C14: S08 | D14: B1 | E14: PREORDER | F14: 10 | G14: 10 | H14: 12.5 | I14: PAID_DUITNOW | J14: DELIVERED | K14: 1184 | L14: VOICE_FOUNDER | M14: Sent voice note, confirmed by phone | N14: =H14*G14 | O14: =(H14-VLOOKUP(D14,'0_SKU'!$A$2:$C$7,3,FALSE))*G14 | P14: =VLOOKUP(D14,'0_SKU'!$A$2:$C$7,3,FALSE)*G14
A15: B01 | B15: 2026-10-15 | C15: S09 | D15: D1 | E15: PREORDER | F15: 8 | G15: 8 | H15: 21 | I15: PAID_DUITNOW | J15: DELIVERED | K15: 6309 | L15: TEXT | M15: Kopi stall evaporated/condensed milk | N15: =H15*G15 | O15: =(H15-VLOOKUP(D15,'0_SKU'!$A$2:$C$7,3,FALSE))*G15 | P15: =VLOOKUP(D15,'0_SKU'!$A$2:$C$7,3,FALSE)*G15
A16: B01 | B16: 2026-10-15 | C16: S09 | D16: B1 | E16: PREORDER | F16: 4 | G16: 4 | H16: 12.5 | I16: PAID_DUITNOW | J16: DELIVERED | K16: 6309 | L16: TEXT | M16: Toast takeaway boxes | N16: =H16*G16 | O16: =(H16-VLOOKUP(D16,'0_SKU'!$A$2:$C$7,3,FALSE))*G16 | P16: =VLOOKUP(D16,'0_SKU'!$A$2:$C$7,3,FALSE)*G16
A17: B02 | B17: 2026-10-22 | C17: S01 | D17: A1 | E17: PREORDER | F17: 12 | G17: 12 | H17: 15 | I17: PAID_DUITNOW | J17: DELIVERED | K17: 7731 | L17: TEXT | M17: Reordered +2 bundles vs B01 | N17: =H17*G17 | O17: =(H17-VLOOKUP(D17,'0_SKU'!$A$2:$C$7,3,FALSE))*G17 | P17: =VLOOKUP(D17,'0_SKU'!$A$2:$C$7,3,FALSE)*G17
A18: B02 | B18: 2026-10-22 | C18: S01 | D18: D1 | E18: PREORDER | F18: 8 | G18: 8 | H18: 21 | I18: PAID_DUITNOW | J18: DELIVERED | K18: 7731 | L18: TEXT | M18: Full carton milk order | N18: =H18*G18 | O18: =(H18-VLOOKUP(D18,'0_SKU'!$A$2:$C$7,3,FALSE))*G18 | P18: =VLOOKUP(D18,'0_SKU'!$A$2:$C$7,3,FALSE)*G18
A19: B02 | B19: 2026-10-22 | C19: S02 | D19: B1 | E19: PREORDER | F19: 8 | G19: 8 | H19: 12.5 | I19: PAID_CASH | J19: DELIVERED | L19: TEXT | M19: Switched from voice to text | N19: =H19*G19 | O19: =(H19-VLOOKUP(D19,'0_SKU'!$A$2:$C$7,3,FALSE))*G19 | P19: =VLOOKUP(D19,'0_SKU'!$A$2:$C$7,3,FALSE)*G19
A20: B02 | B20: 2026-10-22 | C20: S02 | D20: E1 | E20: PREORDER | F20: 5 | G20: 5 | H20: 10.5 | I20: PAID_CASH | J20: DELIVERED | L20: TEXT | M20: Regular bag restock | N20: =H20*G20 | O20: =(H20-VLOOKUP(D20,'0_SKU'!$A$2:$C$7,3,FALSE))*G20 | P20: =VLOOKUP(D20,'0_SKU'!$A$2:$C$7,3,FALSE)*G20
A21: B02 | B21: 2026-10-22 | C21: S03 | D21: C1 | E21: PREORDER | F21: 12 | G21: 12 | H21: 13.5 | I21: PAID_CASH | J21: DELIVERED | L21: TEXT | M21: Upgraded to full master carton (12 bundles) | N21: =H21*G21 | O21: =(H21-VLOOKUP(D21,'0_SKU'!$A$2:$C$7,3,FALSE))*G21 | P21: =VLOOKUP(D21,'0_SKU'!$A$2:$C$7,3,FALSE)*G21
A22: B02 | B22: 2026-10-22 | C22: S04 | D22: A1 | E22: PREORDER | F22: 9 | G22: 9 | H22: 15 | I22: PAID_DUITNOW | J22: DELIVERED | K22: 8842 | L22: TEXT | M22: Used 1 bundle from B01 buffer | N22: =H22*G22 | O22: =(H22-VLOOKUP(D22,'0_SKU'!$A$2:$C$7,3,FALSE))*G22 | P22: =VLOOKUP(D22,'0_SKU'!$A$2:$C$7,3,FALSE)*G22
A23: B02 | B23: 2026-10-22 | C23: S04 | D23: A2 | E23: PREORDER | F23: 10 | G23: 10 | H23: 13.5 | I23: PAID_DUITNOW | J23: DELIVERED | K23: 8842 | L23: TEXT | M23: Smoothie cups | N23: =H23*G23 | O23: =(H23-VLOOKUP(D23,'0_SKU'!$A$2:$C$7,3,FALSE))*G23 | P23: =VLOOKUP(D23,'0_SKU'!$A$2:$C$7,3,FALSE)*G23
A24: B02 | B24: 2026-10-22 | C24: S05 | D24: B1 | E24: PREORDER | F24: 6 | G24: 6 | H24: 12.5 | I24: PAID_CASH | J24: DELIVERED | L24: TEXT | M24: Right-sized order, paid full cash | N24: =H24*G24 | O24: =(H24-VLOOKUP(D24,'0_SKU'!$A$2:$C$7,3,FALSE))*G24 | P24: =VLOOKUP(D24,'0_SKU'!$A$2:$C$7,3,FALSE)*G24
A25: B02 | B25: 2026-10-22 | C25: S06 | D25: A1 | E25: PREORDER | F25: 10 | G25: 10 | H25: 15 | I25: PAID_DUITNOW | J25: DELIVERED | K25: 2049 | L25: TEXT | M25: Paid QR before runner unloaded | N25: =H25*G25 | O25: =(H25-VLOOKUP(D25,'0_SKU'!$A$2:$C$7,3,FALSE))*G25 | P25: =VLOOKUP(D25,'0_SKU'!$A$2:$C$7,3,FALSE)*G25
A26: B02 | B26: 2026-10-22 | C26: S06 | D26: A2 | E26: PREORDER | F26: 11 | G26: 11 | H26: 13.5 | I26: PAID_DUITNOW | J26: DELIVERED | K26: 2049 | L26: TEXT | M26: Used 1 bundle from B01 buffer | N26: =H26*G26 | O26: =(H26-VLOOKUP(D26,'0_SKU'!$A$2:$C$7,3,FALSE))*G26 | P26: =VLOOKUP(D26,'0_SKU'!$A$2:$C$7,3,FALSE)*G26
A27: B02 | B27: 2026-10-22 | C27: S07 | D27: C1 | E27: PREORDER | F27: 13 | G27: 13 | H27: 13.5 | I27: PAID_CASH | J27: DELIVERED | L27: TEXT | M27: 1 ctn + 1 bundle from B01 buffer | N27: =H27*G27 | O27: =(H27-VLOOKUP(D27,'0_SKU'!$A$2:$C$7,3,FALSE))*G27 | P27: =VLOOKUP(D27,'0_SKU'!$A$2:$C$7,3,FALSE)*G27
A28: B02 | B28: 2026-10-22 | C28: S07 | D28: E1 | E28: PREORDER | F28: 5 | G28: 5 | H28: 10.5 | I28: PAID_CASH | J28: DELIVERED | L28: TEXT | M28: Singlet bags | N28: =H28*G28 | O28: =(H28-VLOOKUP(D28,'0_SKU'!$A$2:$C$7,3,FALSE))*G28 | P28: =VLOOKUP(D28,'0_SKU'!$A$2:$C$7,3,FALSE)*G28
A29: B02 | B29: 2026-10-22 | C29: S08 | D29: B1 | E29: PREORDER | F29: 10 | G29: 6 | H29: 12.5 | I29: PAID_DUITNOW | J29: PARTIAL | K29: 3319 | L29: VOICE_CONFIRMED | M29: Wholesaler short 1 ctn B1; used B01 buffer | N29: =H29*G29 | O29: =(H29-VLOOKUP(D29,'0_SKU'!$A$2:$C$7,3,FALSE))*G29 | P29: =VLOOKUP(D29,'0_SKU'!$A$2:$C$7,3,FALSE)*G29
A30: B02 | B30: 2026-10-22 | C30: S09 | D30: D1 | E30: PREORDER | F30: 10 | G30: 10 | H30: 21 | I30: PAID_DUITNOW | J30: DELIVERED | K30: 9951 | L30: TEXT | M30: 1 ctn + 2 bundles from B01 buffer | N30: =H30*G30 | O30: =(H30-VLOOKUP(D30,'0_SKU'!$A$2:$C$7,3,FALSE))*G30 | P30: =VLOOKUP(D30,'0_SKU'!$A$2:$C$7,3,FALSE)*G30
A31: B02 | B31: 2026-10-22 | C31: S09 | D31: B1 | E31: PREORDER | F31: 4 | G31: 4 | H31: 12.5 | I31: PAID_DUITNOW | J31: DELIVERED | K31: 9951 | L31: TEXT | M31: Toast boxes | N31: =H31*G31 | O31: =(H31-VLOOKUP(D31,'0_SKU'!$A$2:$C$7,3,FALSE))*G31 | P31: =VLOOKUP(D31,'0_SKU'!$A$2:$C$7,3,FALSE)*G31
A32: B02 | B32: 2026-10-22 | C32: S10 | D32: C1 | E32: SPOT | F32: 2 | G32: 2 | H32: 13.5 | I32: PAID_CASH | J32: DELIVERED | L32: SPOT | M32: Walk-up spot sale from B01 buffer stock | N32: =H32*G32 | O32: =(H32-VLOOKUP(D32,'0_SKU'!$A$2:$C$7,3,FALSE))*G32 | P32: =VLOOKUP(D32,'0_SKU'!$A$2:$C$7,3,FALSE)*G32

Sheet 3_PO
A1: batch_id | B1: sku_code | C1: cartons_ordered | D1: cartons_received | E1: carton_cost | F1: carton_geometric_liters | G1: physical_boxes_per_carton | H1: cash_paid | I1: total_geometric_liters | J1: total_physical_boxes
A2: B01 | B2: A1 | C2: 3 | D2: 3 | E2: 135 | F2: 92.5 | G2: 2 | H2: =D2*E2 | I2: =D2*F2 | J2: =D2*G2
A3: B01 | B3: A2 | C3: 2 | D3: 2 | E3: 120 | F3: 84 | G3: 2 | H3: =D3*E3 | I3: =D3*F3 | J3: =D3*G3
A4: B01 | B4: B1 | C4: 3 | D4: 3 | E4: 110 | F4: 76 | G4: 1 | H4: =D4*E4 | I4: =D4*F4 | J4: =D4*G4
A5: B01 | B5: C1 | C5: 2 | D5: 2 | E5: 144 | F5: 68.5 | G5: 1 | H5: =D5*E5 | I5: =D5*F5 | J5: =D5*G5
A6: B01 | B6: D1 | C6: 2 | D6: 2 | E6: 160 | F6: 28 | G6: 1 | H6: =D6*E6 | I6: =D6*F6 | J6: =D6*G6
A7: B01 | B7: E1 | C7: 1 | D7: 1 | E7: 90 | F7: 35 | G7: 1 | H7: =D7*E7 | I7: =D7*F7 | J7: =D7*G7
A8: B02 | B8: A1 | C8: 3 | D8: 3 | E8: 135 | F8: 92.5 | G8: 2 | H8: =D8*E8 | I8: =D8*F8 | J8: =D8*G8
A9: B02 | B9: A2 | C9: 2 | D9: 2 | E9: 120 | F9: 84 | G9: 2 | H9: =D9*E9 | I9: =D9*F9 | J9: =D9*G9
A10: B02 | B10: B1 | C10: 3 | D10: 2 | E10: 110 | F10: 76 | G10: 1 | H10: =D10*E10 | I10: =D10*F10 | J10: =D10*G10
A11: B02 | B11: C1 | C11: 2 | D11: 2 | E11: 144 | F11: 68.5 | G11: 1 | H11: =D11*E11 | I11: =D11*F11 | J11: =D11*G11
A12: B02 | B12: D1 | C12: 2 | D12: 2 | E12: 160 | F12: 28 | G12: 1 | H12: =D12*E12 | I12: =D12*F12 | J12: =D12*G12
A13: B02 | B13: E1 | C13: 1 | D13: 1 | E13: 90 | F13: 35 | G13: 1 | H13: =D13*E13 | I13: =D13*F13 | J13: =D13*G13

Sheet 4_Batch_PnL
A1: batch_id | B1: gmv_delivered | C1: cogs_cash | D1: realized_gp | E1: opening_buffer_cost | F1: closing_buffer_cost | G1: cash_collected | H1: runner_paid | I1: net_cash | J1: identity_check
A2: B01 | B2: =SUMIFS('2_Orders'!$N:$N, '2_Orders'!$A:$A, $A2) | C2: =SUMIFS('3_PO'!$H:$H, '3_PO'!$A:$A, $A2) | D2: =SUMIFS('2_Orders'!$O:$O, '2_Orders'!$A:$A, $A2) | E2: 0 | F2: =E2 + C2 - SUMIFS('2_Orders'!$P:$P, '2_Orders'!$A:$A, $A2) | G2: =B2 | H2: 42.5 | I2: =G2 - C2 - H2 | J2: =D2 - (F2 - E2) - H2 - I2
A3: B02 | B3: =SUMIFS('2_Orders'!$N:$N, '2_Orders'!$A:$A, $A3) | C3: =SUMIFS('3_PO'!$H:$H, '3_PO'!$A:$A, $A3) | D3: =SUMIFS('2_Orders'!$O:$O, '2_Orders'!$A:$A, $A3) | E3: =F2 | F3: =E3 + C3 - SUMIFS('2_Orders'!$P:$P, '2_Orders'!$A:$A, $A3) | G3: =B3 | H3: 42.5 | I3: =G3 - C3 - H3 | J3: =D3 - (F3 - E3) - H3 - I3

Sheet 5_Gate
A1: batch_id | B1: gmv_delivered | C1: gmv_pass | D1: realized_gp | E1: gp_pass | F1: batch_pass | G1: stalls_active
A2: B01 | B2: ='4_Batch_PnL'!B2 | C2: =B2>=1500 | D2: ='4_Batch_PnL'!D2 | E2: =D2>=150 | F2: =AND(C2,E2) | G2: 9
A3: B02 | B3: ='4_Batch_PnL'!B3 | C3: =B3>=1500 | D3: ='4_Batch_PnL'!D3 | E3: =D3>=150 | F3: =AND(C3,E3) | G3: 9
A5: PHASE 2 GATE VERDICT
A6: Gate Requirement | B6: Consecutive Pass Count | C6: Gate Status | D6: Next Required Action
A7: >= RM 1,500 GMV & >= RM 150 GP (2 consecutive weeks) | B7: =COUNTIF(F2:F3, TRUE) | C7: =IF(AND(F2,F3), "GATE CLEARED", "GATE FAILED") | D7: =IF(AND(F2,F3), "Proceed to Phase 2 (/to-spec)", IF(AND(NOT(AND(C2,C3)), AND(E2,E3)), "Volume problem — recruit Stalls, don't build", IF(AND(AND(C2,C3), NOT(AND(E2,E3))), "Margin problem — renegotiate cost, don't build", "The model needs revisiting before any code")))
A9: Gate Benchmark Summary (RM)
A10: Batch | B10: Delivered GMV (RM) | C10: GMV Gate Min (RM) | D10: Realized GP (RM) | E10: GP Gate Min (RM)
A11: B01 | B11: 1657 | C11: 1500 | D11: 167 | E11: 150
A12: B02 | B12: 1896 | C12: 1500 | D12: 187.5 | E12: 150

Sheet 6_Observations
A1: batch_id | B1: delivery_date | C1: q1_stalls_approached_vs_yes | D1: q2_first_sku_asked | E1: q3_price_objections_by_sku | F1: q4_voice_notes_received_vs_confirmed | G1: q5_vehicle_fit_measured_vs_estimated_liters | H1: q6_supplier_thursday_shortfalls | I1: q7_shift_duration_vs_2_75h_model | J1: q8_late_or_unpaid_stalls
A2: B01 | B2: 2026-10-15 | C2: Approached 22 stalls across Premier 101 & Gala City; 9 preordered (40.9% conversion). | D2: Drink stalls asked for D1 (milk) and A1 (22oz cups) first; food stalls asked for B1 (750ml boxes). | E2: S03 noted C1 was only RM 0.50 cheaper than their current supplier, but still bought for doorstep delivery. | F2: 2 voice orders arrived (S02, S08); 0 confirmed via text read-back until founder called them directly (VOICE_FOUNDER). | G2: 13 master cartons (18 physical boxes) = 901.5L geometric (~980L packed). Barely fit in a Myvi with rear seats flat; needed front passenger seat. | H2: 100% fill rate at the wholesaler loading bay on Thursday morning. | I2: Total shift took 3.20 hours (vs 2.75h modelled). Delayed by hunting unit numbers in Gala City & waiting for busy stalls to scan DuitNow QR. | J2: S05 (Provisional) ordered 8 bundles of B1 but only had RM 50 cash on hand; downgraded delivery to 4 bundles on the spot (4 bundles to buffer).
A3: B02 | B3: 2026-10-22 | C3: Approached 4 additional stalls in Gala City; 1 preordered, 1 bought walk-up spot (S10) from car buffer. | D3: D1 remains the #1 door-opener for drink stalls, immediately pulling through high-margin A1 and A2 cup orders. | E3: Zero price objections on D1 (4.8% margin is thin for us, but makes our price unbeatable). S03 upgraded C1 order to a full carton (12 bundles). | F3: 1 voice note arrived (S08) and confirmed read-back via text (VOICE_CONFIRMED). S02 switched to regular WhatsApp text. ADR-0014 voice bot not needed yet. | G3: 12 master cartons (17 physical boxes) = 825.5L geometric + B01 buffer fit cleanly once loaded in reverse drop sequence by cluster. | H3: Wholesaler was short 1 master carton of B1 (ordered 3, received 2). Used 4 bundles of B1 from B01 buffer to cover S02/S05/S09; only S08 was partially shorted (6/10 delivered). | I3: Total shift took 2.50 hours (beat the 2.75h model). Dropping bundles first and collecting DuitNow after completing the cluster loop saved 40 mins. | J3: 100% paid on delivery. S01 and S06 paid via DuitNow QR before the runner even finished unloading.
A5: SIDE-BY-SIDE FIELD REVIEW MATRIX (SPEC SECTION 8)
A6: Question | B6: Why it matters (Spec Reference) | C6: B01 Observation (2026-10-15) | D6: B02 Observation (2026-10-22)
A7: How many Stalls did you approach, and how many said yes? | B7: Conversion rate. If it is 1 in 10, 14 Stalls is 140 conversations | C7: Approached 22 stalls across Premier 101 & Gala City; 9 preordered (40.9% conversion). | D7: Approached 4 additional stalls in Gala City; 1 preordered, 1 bought walk-up spot (S10) from car buffer.
A8: Which SKU did each Stall ask for first? | B8: Tell the Anchor pitch from the actual first ask | C8: Drink stalls asked for D1 (milk) and A1 (22oz cups) first; food stalls asked for B1 (750ml boxes). | D8: D1 remains the #1 door-opener for drink stalls, immediately pulling through high-margin A1 and A2 cup orders.
A9: Did any Stall object to the price? Which SKU? | B9: Tests whether 4.8% on D1 is too thin to sell | C9: S03 noted C1 was only RM 0.50 cheaper than their current supplier, but still bought for doorstep delivery. | D9: Zero price objections on D1 (4.8% margin is thin for us, but makes our price unbeatable). S03 upgraded C1 order to a full carton (12 bundles).
A10: How many voice notes arrived, and how many confirmed? | B10: ADR-0014 viability | C10: 2 voice orders arrived (S02, S08); 0 confirmed via text read-back until founder called them directly (VOICE_FOUNDER). | D10: 1 voice note arrived (S08) and confirmed read-back via text (VOICE_CONFIRMED). S02 switched to regular WhatsApp text. ADR-0014 voice bot not needed yet.
A11: Did cartons fit the vehicle? Measured litres vs estimated? | B11: Validates ADR-0015 | C11: 13 master cartons (18 physical boxes) = 901.5L geometric (~980L packed). Barely fit in a Myvi with rear seats flat; needed front passenger seat. | D11: 12 master cartons (17 physical boxes) = 825.5L geometric + B01 buffer fit cleanly once loaded in reverse drop sequence by cluster.
A12: Did the supplier have everything on Thursday? | B12: Shortfall frequency (ADR-0011) | C12: 100% fill rate at the wholesaler loading bay on Thursday morning. | D12: Wholesaler was short 1 master carton of B1 (ordered 3, received 2). Used 4 bundles of B1 from B01 buffer to cover S02/S05/S09; only S08 was partially shorted (6/10 delivered).
A13: What took longer than expected? | B13: Real shift duration vs the modelled 2.75 h | C13: Total shift took 3.20 hours (vs 2.75h modelled). Delayed by hunting unit numbers in Gala City & waiting for busy stalls to scan DuitNow QR. | D13: Total shift took 2.50 hours (beat the 2.75h model). Dropping bundles first and collecting DuitNow after completing the cluster loop saved 40 mins.
A14: Did any Stall pay late or not at all? | B14: Trust-tier calibration | C14: S05 (Provisional) ordered 8 bundles of B1 but only had RM 50 cash on hand; downgraded delivery to 4 bundles on the spot (4 bundles to buffer). | D14: 100% paid on delivery. S01 and S06 paid via DuitNow QR before the runner even finished unloading.
